zepben/evolve/__init__.py
zepben/evolve/exceptions.py
zepben/evolve/types.py
zepben/evolve/util.py
zepben/evolve/database/__init__.py
zepben/evolve/database/paths/__init__.py
zepben/evolve/database/paths/database_type.py
zepben/evolve/database/paths/ewb_data_file_paths.py
zepben/evolve/database/sqlite/__init__.py
zepben/evolve/database/sqlite/common/__init__.py
zepben/evolve/database/sqlite/common/base_cim_reader.py
zepben/evolve/database/sqlite/common/base_cim_writer.py
zepben/evolve/database/sqlite/common/base_collection_reader.py
zepben/evolve/database/sqlite/common/base_collection_writer.py
zepben/evolve/database/sqlite/common/base_database_reader.py
zepben/evolve/database/sqlite/common/base_database_tables.py
zepben/evolve/database/sqlite/common/base_database_writer.py
zepben/evolve/database/sqlite/common/base_entry_writer.py
zepben/evolve/database/sqlite/common/base_service_reader.py
zepben/evolve/database/sqlite/common/base_service_writer.py
zepben/evolve/database/sqlite/common/metadata_collection_reader.py
zepben/evolve/database/sqlite/common/metadata_collection_writer.py
zepben/evolve/database/sqlite/common/metadata_entry_reader.py
zepben/evolve/database/sqlite/common/metadata_entry_writer.py
zepben/evolve/database/sqlite/common/reader_exceptions.py
zepben/evolve/database/sqlite/customer/__init__.py
zepben/evolve/database/sqlite/customer/customer_cim_reader.py
zepben/evolve/database/sqlite/customer/customer_cim_writer.py
zepben/evolve/database/sqlite/customer/customer_database_reader.py
zepben/evolve/database/sqlite/customer/customer_database_tables.py
zepben/evolve/database/sqlite/customer/customer_database_writer.py
zepben/evolve/database/sqlite/customer/customer_service_reader.py
zepben/evolve/database/sqlite/customer/customer_service_writer.py
zepben/evolve/database/sqlite/diagram/__init__.py
zepben/evolve/database/sqlite/diagram/diagram_cim_reader.py
zepben/evolve/database/sqlite/diagram/diagram_cim_writer.py
zepben_evolve-0.48.0.dist-info/licenses/LICENSE
zepben_evolve-0.48.0.dist-info/METADATA
zepben_evolve-0.48.0.dist-info/WHEEL
zepben_evolve-0.48.0.dist-info/top_level.txt
zepben_evolve-0.48.0.dist-info/RECORD
