Metadata-Version: 2.4
Name: zepben.evolve
Version: 0.48.0
Summary: Python SDK for interacting with the Evolve platform
Home-page: https://github.com/zepben/evolve-sdk-python
Author: Kurt Greaves
Author-email: kurt.greaves@zepben.com
License: MPL 2.0
Classifier: License :: OSI Approved :: Mozilla Public License 2.0 (MPL 2.0)
Classifier: Programming Language :: Python :: 3
Classifier: Programming Language :: Python :: 3.9
Classifier: Programming Language :: Python :: 3.10
Classifier: Programming Language :: Python :: 3.11
Classifier: Operating System :: OS Independent
Requires-Python: >=3.9,<3.13
License-File: LICENSE
Requires-Dist: zepben.auth==0.12.1
Requires-Dist: zepben-protobuf==0.37.0
Requires-Dist: typing_extensions==4.12.2
Provides-Extra: test
Requires-Dist: pytest==7.1.2; extra == "test"
Requires-Dist: pytest-cov==2.10.1; extra == "test"
Requires-Dist: pytest-asyncio==0.19.0; extra == "test"
Requires-Dist: pytest-timeout==1.4.2; extra == "test"
Requires-Dist: pytest-subtests; extra == "test"
Requires-Dist: hypothesis==6.56.3; extra == "test"
Requires-Dist: grpcio-testing==1.61.3; extra == "test"
Requires-Dist: pylint==2.14.5; extra == "test"
Requires-Dist: six==1.16.0; extra == "test"
Requires-Dist: tox; extra == "test"
Dynamic: author
Dynamic: author-email
Dynamic: classifier
Dynamic: description
Dynamic: description-content-type
Dynamic: home-page
Dynamic: license
Dynamic: license-file
Dynamic: provides-extra
Dynamic: requires-dist
Dynamic: requires-python
Dynamic: summary
